{
  "db_name": "PostgreSQL",
  "query": "select project_id, project_name from project where team_id = $1",
  "describe": {
    "columns": [
      {
        "ordinal": 0,
        "name": "project_id",
        "type_info": "Uuid"
      },
      {
        "ordinal": 1,
        "name": "project_name",
        "type_info": "Text"
      }
    ],
    "parameters": {
      "Left": [
        "Uuid"
      ]
    },
    "nullable": [
      false,
      false
    ]
  },
  "hash": "541a838fa86ef18c4502be165642713c14b7b90b61a0513c2cb42a3b7cb1d5d0"
}
