{
  "db_name": "PostgreSQL",
  "query": "select\n            character_id,\n            character_name,\n            settings,\n            project_id,\n            created_at \"created_at: Timestamptz\",\n            updated_at \"updated_at: Timestamptz\"\n        from character where project_id = $1",
  "describe": {
    "columns": [
      {
        "ordinal": 0,
        "name": "character_id",
        "type_info": "Uuid"
      },
      {
        "ordinal": 1,
        "name": "character_name",
        "type_info": "Text"
      },
      {
        "ordinal": 2,
        "name": "settings",
        "type_info": "Jsonb"
      },
      {
        "ordinal": 3,
        "name": "project_id",
        "type_info": "Uuid"
      },
      {
        "ordinal": 4,
        "name": "created_at: Timestamptz",
        "type_info": "Timestamptz"
      },
      {
        "ordinal": 5,
        "name": "updated_at: Timestamptz",
        "type_info": "Timestamptz"
      }
    ],
    "parameters": {
      "Left": [
        "Uuid"
      ]
    },
    "nullable": [
      false,
      false,
      false,
      false,
      false,
      true
    ]
  },
  "hash": "bbca122ffd1634966810de57e2204345cd82e1cbe8ac716b36e0a2f76c382b2e"
}
